generate_od/__init__.py
generate_od/generator.py
generate_od/model.py
generate_od/sateimgs.py
generate_od/utils.py
generate_od/worldpop.py
generate_od-0.1.1.dist-info/LICENSE
generate_od-0.1.1.dist-info/METADATA
generate_od-0.1.1.dist-info/WHEEL
generate_od-0.1.1.dist-info/top_level.txt
generate_od-0.1.1.dist-info/RECORD
