Metadata-Version: 2.1
Name: generate-od
Version: 0.1.1
Summary: A tool to generate origin-destination matrix for any given area.
Home-page: https://github.com/tsinghua-fib-lab/generate-od-pubtools
Author: Can Rong
Author-email: 276413973@qq.com
Classifier: Programming Language :: Python :: 3.8
Classifier: License :: OSI Approved :: MIT License
Classifier: Operating System :: OS Independent
Classifier: Intended Audience :: Science/Research
Classifier: Intended Audience :: Developers
Classifier: Topic :: Scientific/Engineering
Classifier: Topic :: Scientific/Engineering :: GIS
Classifier: Topic :: Scientific/Engineering :: Artificial Intelligence
Requires-Python: >=3.8
License-File: LICENSE
Requires-Dist: geopandas
Requires-Dist: open-clip-torch (>=2.23.0)
Requires-Dist: huggingface-hub
Requires-Dist: numpy
Requires-Dist: torch (>=2.1.0)
Requires-Dist: Pillow
Requires-Dist: scipy
Requires-Dist: shapely
Requires-Dist: scikit-learn (==1.3.0)
Requires-Dist: contextily
Requires-Dist: matplotlib
Requires-Dist: rasterio
